libname/__init__.py
libname/hello.py
okela-0.0.1.dist-info/METADATA
okela-0.0.1.dist-info/WHEEL
okela-0.0.1.dist-info/top_level.txt
okela-0.0.1.dist-info/RECORD
